LICENSE
MANIFEST.in
README.rst
setup.py
rest_client/__init__.py
rest_client/async.py
rest_client.egg-info/PKG-INFO
rest_client.egg-info/SOURCES.txt
rest_client.egg-info/dependency_links.txt
rest_client.egg-info/requires.txt
rest_client.egg-info/top_level.txt