Metadata-Version: 1.1
Name: rest-client
Version: 0.3.5
Summary: RESTful Client for tornado
Home-page: https://github.com/mosquito/rest-client
Author: Dmitry Orlov <me@mosquito.su>
Author-email: me@mosquito.su
License: MIT
Platform: all
Classifier: Environment :: Console
Classifier: Programming Language :: Python :: 2
Classifier: Programming Language :: Python :: 2.7
Classifier: Programming Language :: Python :: 3.1
Classifier: Programming Language :: Python :: 3.2
Classifier: Programming Language :: Python :: 3.4
Classifier: Programming Language :: Python :: 3.5
Classifier: Programming Language :: Python :: Implementation :: PyPy
